{
    "version": 1,
    "type": "MIDI",
    "name": "all_parameters3",
    "index": 2,
    "knobs": [
        {
            "controlIndex": 0,
            "controlMode": 0,
            "controlChannel": 15,
            "controlParam": 51,
            "nrpnAddress": 0,
            "minValue": 0,
            "maxValue": 127,
            "controlName": "ARP Rate",
            "colorScheme": 7,
            "hapticMode": 0,
            "hapticIndent1": 255,
            "hapticIndent2": 255,
            "hapticSteps": 0,
            "stepNames": [
                "",
                "",
                "",
                "",
                "",
                "",
                "",
                "",
                "",
                "",
                "",
                "",
                "",
                "",
                "",
                ""
            ]
        },
        {
            "controlIndex": 1,
            "controlMode": 0,
            "controlChannel": 15,
            "controlParam": 50,
            "nrpnAddress": 0,
            "minValue": 0,
            "maxValue": 127,
            "controlName": "ARP Gate",
            "colorScheme": 7,
            "hapticMode": 0,
            "hapticIndent1": 255,
            "hapticIndent2": 255,
            "hapticSteps": 0,
            "stepNames": [
                "",
                "",
                "",
                "",
                "",
                "",
                "",
                "",
                "",
                "",
                "",
                "",
                "",
                "",
                "",
                ""
            ]
        },
        {
            "controlIndex": 2,
            "controlMode": 0,
            "controlChannel": 15,
            "controlParam": 40,
            "nrpnAddress": 0,
            "minValue": 0,
            "maxValue": 127,
            "controlName": "ARP GateSpr",
            "colorScheme": 7,
            "hapticMode": 0,
            "hapticIndent1": 64,
            "hapticIndent2": 255,
            "hapticSteps": 0,
            "stepNames": [
                "",
                "",
                "",
                "",
                "",
                "",
                "",
                "",
                "",
                "",
                "",
                "",
                "",
                "",
                "",
                ""
            ]
        },
        {
            "controlIndex": 3,
            "controlMode": 0,
            "controlChannel": 15,
            "controlParam": 39,
            "nrpnAddress": 0,
            "minValue": 0,
            "maxValue": 127,
            "controlName": "ARP OctSpr",
            "colorScheme": 7,
            "hapticMode": 0,
            "hapticIndent1": 64,
            "hapticIndent2": 255,
            "hapticSteps": 0,
            "stepNames": [
                "",
                "",
                "",
                "",
                "",
                "",
                "",
                "",
                "",
                "",
                "",
                "",
                "",
                "",
                "",
                ""
            ]
        },
        {
            "controlIndex": 4,
            "controlMode": 0,
            "controlChannel": 15,
            "controlParam": 37,
            "nrpnAddress": 0,
            "minValue": 0,
            "maxValue": 127,
            "controlName": "ARP VelSpr",
            "colorScheme": 7,
            "hapticMode": 0,
            "hapticIndent1": 64,
            "hapticIndent2": 255,
            "hapticSteps": 0,
            "stepNames": [
                "",
                "",
                "",
                "",
                "",
                "",
                "",
                "",
                "",
                "",
                "",
                "",
                "",
                "",
                "",
                ""
            ]
        },
        {
            "controlIndex": 5,
            "controlMode": 0,
            "controlChannel": 15,
            "controlParam": 42,
            "nrpnAddress": 0,
            "minValue": 0,
            "maxValue": 127,
            "controlName": "ARP Rhythm",
            "colorScheme": 7,
            "hapticMode": 0,
            "hapticIndent1": 255,
            "hapticIndent2": 255,
            "hapticSteps": 0,
            "stepNames": [
                "",
                "",
                "",
                "",
                "",
                "",
                "",
                "",
                "",
                "",
                "",
                "",
                "",
                "",
                "",
                ""
            ]
        },
        {
            "controlIndex": 6,
            "controlMode": 0,
            "controlChannel": 15,
            "controlParam": 43,
            "nrpnAddress": 0,
            "minValue": 0,
            "maxValue": 127,
            "controlName": "ARP SeqLen",
            "colorScheme": 7,
            "hapticMode": 0,
            "hapticIndent1": 255,
            "hapticIndent2": 255,
            "hapticSteps": 0,
            "stepNames": [
                "",
                "",
                "",
                "",
                "",
                "",
                "",
                "",
                "",
                "",
                "",
                "",
                "",
                "",
                "",
                ""
            ]
        },
        {
            "controlIndex": 7,
            "controlMode": 0,
            "controlChannel": 15,
            "controlParam": 36,
            "nrpnAddress": 0,
            "minValue": 0,
            "maxValue": 127,
            "controlName": "ARP RevProb",
            "colorScheme": 7,
            "hapticMode": 0,
            "hapticIndent1": 255,
            "hapticIndent2": 255,
            "hapticSteps": 0,
            "stepNames": [
                "",
                "",
                "",
                "",
                "",
                "",
                "",
                "",
                "",
                "",
                "",
                "",
                "",
                "",
                "",
                ""
            ]
        },
        {
            "controlIndex": 8,
            "controlMode": 0,
            "controlChannel": 15,
            "controlParam": 44,
            "nrpnAddress": 0,
            "minValue": 0,
            "maxValue": 127,
            "controlName": "ARP ChoPoly",
            "colorScheme": 7,
            "hapticMode": 0,
            "hapticIndent1": 255,
            "hapticIndent2": 255,
            "hapticSteps": 0,
            "stepNames": [
                "",
                "",
                "",
                "",
                "",
                "",
                "",
                "",
                "",
                "",
                "",
                "",
                "",
                "",
                "",
                ""
            ]
        },
        {
            "controlIndex": 9,
            "controlMode": 0,
            "controlChannel": 15,
            "controlParam": 48,
            "nrpnAddress": 0,
            "minValue": 0,
            "maxValue": 127,
            "controlName": "ARP ChoProb",
            "colorScheme": 7,
            "hapticMode": 0,
            "hapticIndent1": 255,
            "hapticIndent2": 255,
            "hapticSteps": 0,
            "stepNames": [
                "",
                "",
                "",
                "",
                "",
                "",
                "",
                "",
                "",
                "",
                "",
                "",
                "",
                "",
                "",
                ""
            ]
        },
        {
            "controlIndex": 10,
            "controlMode": 0,
            "controlChannel": 15,
            "controlParam": 45,
            "nrpnAddress": 0,
            "minValue": 0,
            "maxValue": 127,
            "controlName": "ARP RatchAm",
            "colorScheme": 7,
            "hapticMode": 0,
            "hapticIndent1": 255,
            "hapticIndent2": 255,
            "hapticSteps": 0,
            "stepNames": [
                "",
                "",
                "",
                "",
                "",
                "",
                "",
                "",
                "",
                "",
                "",
                "",
                "",
                "",
                "",
                ""
            ]
        },
        {
            "controlIndex": 11,
            "controlMode": 0,
            "controlChannel": 15,
            "controlParam": 49,
            "nrpnAddress": 0,
            "minValue": 0,
            "maxValue": 127,
            "controlName": "ARP RatchPr",
            "colorScheme": 7,
            "hapticMode": 0,
            "hapticIndent1": 255,
            "hapticIndent2": 255,
            "hapticSteps": 0,
            "stepNames": [
                "",
                "",
                "",
                "",
                "",
                "",
                "",
                "",
                "",
                "",
                "",
                "",
                "",
                "",
                "",
                ""
            ]
        },
        {
            "controlIndex": 12,
            "controlMode": 0,
            "controlChannel": 15,
            "controlParam": 46,
            "nrpnAddress": 0,
            "minValue": 0,
            "maxValue": 127,
            "controlName": "ARP NoteProb",
            "colorScheme": 7,
            "hapticMode": 0,
            "hapticIndent1": 255,
            "hapticIndent2": 255,
            "hapticSteps": 0,
            "stepNames": [
                "",
                "",
                "",
                "",
                "",
                "",
                "",
                "",
                "",
                "",
                "",
                "",
                "",
                "",
                "",
                ""
            ]
        },
        {
            "controlIndex": 13,
            "controlMode": 0,
            "controlChannel": 15,
            "controlParam": 47,
            "nrpnAddress": 0,
            "minValue": 0,
            "maxValue": 127,
            "controlName": "ARP BassProb",
            "colorScheme": 7,
            "hapticMode": 0,
            "hapticIndent1": 255,
            "hapticIndent2": 255,
            "hapticSteps": 0,
            "stepNames": [
                "",
                "",
                "",
                "",
                "",
                "",
                "",
                "",
                "",
                "",
                "",
                "",
                "",
                "",
                "",
                ""
            ]
        }
    ],
    "buttons": []
}